.gitignore
README.md
setup.py
eboxbw/__init__.py
eboxbw/cli.py
eboxbw/eboxbw.py
eboxbw.egg-info/PKG-INFO
eboxbw.egg-info/SOURCES.txt
eboxbw.egg-info/dependency_links.txt
eboxbw.egg-info/entry_points.txt
eboxbw.egg-info/requires.txt
eboxbw.egg-info/top_level.txt