Metadata-Version: 1.0
Name: eboxbw
Version: 2.3.6
Summary: Electronic Box cable Internet bandwidth usage
Home-page: https://github.com/eepp/eboxbw
Author: Philippe Proulx
Author-email: eeppeliteloop@gmail.com
License: UNKNOWN
Platform: UNKNOWN
